pytest_zeebe/__init__.py
pytest_zeebe/assertion.py
pytest_zeebe/assertions/__init__.py
pytest_zeebe/assertions/process_instance_assert.py
pytest_zeebe/client/__init__.py
pytest_zeebe/client/client_grpc/__init__.py
pytest_zeebe/client/client_grpc/pytest_zeebe_gateway.proto
pytest_zeebe/client/client_grpc/pytest_zeebe_gateway_pb2.py
pytest_zeebe/client/client_grpc/pytest_zeebe_gateway_pb2.pyi
pytest_zeebe/client/client_grpc/pytest_zeebe_gateway_pb2_grpc.py
pytest_zeebe/client/zeebe_test_client.py
pytest_zeebe/engine/__init__.py
pytest_zeebe/engine/engine_control_grpc/__init__.py
pytest_zeebe/engine/engine_control_grpc/pytest_zeebe_engine_control.proto
pytest_zeebe/engine/engine_control_grpc/pytest_zeebe_engine_control_pb2.py
pytest_zeebe/engine/engine_control_grpc/pytest_zeebe_engine_control_pb2.pyi
pytest_zeebe/engine/engine_control_grpc/pytest_zeebe_engine_control_pb2_grpc.py
pytest_zeebe/engine/zeebe_test_engine.py
pytest_zeebe/filters/__init__.py
pytest_zeebe/filters/incident_filter.py
pytest_zeebe/filters/process_instance_filter.py
pytest_zeebe/filters/process_message_subscription_filter.py
pytest_zeebe/filters/variable_filter.py
pytest_zeebe/fixtures.py
pytest_zeebe-0.1.2.dist-info/LICENSE
pytest_zeebe-0.1.2.dist-info/METADATA
pytest_zeebe-0.1.2.dist-info/WHEEL
pytest_zeebe-0.1.2.dist-info/entry_points.txt
pytest_zeebe-0.1.2.dist-info/RECORD
